riverboard/__init__.py
riverboard/cli.py
riverboard/riverboard.py
riverboard-0.0.0.dist-info/AUTHORS.rst
riverboard-0.0.0.dist-info/LICENSE
riverboard-0.0.0.dist-info/METADATA
riverboard-0.0.0.dist-info/WHEEL
riverboard-0.0.0.dist-info/entry_points.txt
riverboard-0.0.0.dist-info/top_level.txt
riverboard-0.0.0.dist-info/RECORD
