Metadata-Version: 2.1
Name: riverboard
Version: 0.0.0
Summary: Board for River library
Home-page: https://github.com/sylwekczmil/riverboard
Author: Sylwester Czmil
Author-email: sylwekczmil@gmail.com
License: BSD license
Keywords: riverboard
Platform: UNKNOWN
Classifier: Development Status :: 2 - Pre-Alpha
Classifier: Intended Audience :: Developers
Classifier: License :: OSI Approved :: BSD License
Classifier: Natural Language :: English
Classifier: Programming Language :: Python :: 3
Classifier: Programming Language :: Python :: 3.6
Classifier: Programming Language :: Python :: 3.7
Classifier: Programming Language :: Python :: 3.8
Requires-Python: >=3.6
License-File: LICENSE
License-File: AUTHORS.rst
Requires-Dist: Click (>=7.0)
